fds/__init__.py
fds/sdk/__init__.py
fds/sdk/FactSetBenchmarks/__init__.py
fds/sdk/FactSetBenchmarks/api_client.py
fds/sdk/FactSetBenchmarks/configuration.py
fds/sdk/FactSetBenchmarks/exceptions.py
fds/sdk/FactSetBenchmarks/model_utils.py
fds/sdk/FactSetBenchmarks/rest.py
fds/sdk/FactSetBenchmarks/api/__init__.py
fds/sdk/FactSetBenchmarks/api/benchmark_constituents_api.py
fds/sdk/FactSetBenchmarks/api/helper_api.py
fds/sdk/FactSetBenchmarks/api/index_level_api.py
fds/sdk/FactSetBenchmarks/apis/__init__.py
fds/sdk/FactSetBenchmarks/model/__init__.py
fds/sdk/FactSetBenchmarks/model/benchmark_constituent.py
fds/sdk/FactSetBenchmarks/model/benchmark_constituents_request.py
fds/sdk/FactSetBenchmarks/model/benchmark_constituents_response.py
fds/sdk/FactSetBenchmarks/model/benchmark_id_list.py
fds/sdk/FactSetBenchmarks/model/benchmark_id_list_request.py
fds/sdk/FactSetBenchmarks/model/benchmark_id_list_response.py
fds/sdk/FactSetBenchmarks/model/benchmark_ratios.py
fds/sdk/FactSetBenchmarks/model/benchmark_ratios_request.py
fds/sdk/FactSetBenchmarks/model/benchmark_ratios_response.py
fds/sdk/FactSetBenchmarks/model/calendar.py
fds/sdk/FactSetBenchmarks/model/constituent_ids.py
fds/sdk/FactSetBenchmarks/model/error_response.py
fds/sdk/FactSetBenchmarks/model/error_response_sub_errors.py
fds/sdk/FactSetBenchmarks/model/family_filter.py
fds/sdk/FactSetBenchmarks/model/fi_constituent_ids.py
fds/sdk/FactSetBenchmarks/model/fixed_income_benchmark_constituent.py
fds/sdk/FactSetBenchmarks/model/fixed_income_benchmark_constituents_request.py
fds/sdk/FactSetBenchmarks/model/fixed_income_benchmark_constituents_response.py
fds/sdk/FactSetBenchmarks/model/frequency.py
fds/sdk/FactSetBenchmarks/model/hedge_type.py
fds/sdk/FactSetBenchmarks/model/implied_date.py
fds/sdk/FactSetBenchmarks/model/index_history.py
fds/sdk/FactSetBenchmarks/model/index_history_request.py
fds/sdk/FactSetBenchmarks/model/index_history_response.py
fds/sdk/FactSetBenchmarks/model/index_ids.py
fds.sdk.FactSetBenchmarks-1.5.0.dist-info/LICENSE
fds.sdk.FactSetBenchmarks-1.5.0.dist-info/METADATA
fds.sdk.FactSetBenchmarks-1.5.0.dist-info/WHEEL
fds.sdk.FactSetBenchmarks-1.5.0.dist-info/top_level.txt
fds.sdk.FactSetBenchmarks-1.5.0.dist-info/RECORD
